<?xml version="1.0" encoding="UTF-8"?>
<!-- generated on 2019-05-06 09:46:32.542596 by $Id$ via randomTrips.py
  options: 
-->
<routes xmlns:xsi="http://www.w3.org/2001/XMLSchema-instance" xsi:noNamespaceSchemaLocation="http://sumo.dlr.de/xsd/routes_file.xsd">
    <vType id="veh_passenger" vClass="passenger">
    </vType>
    <trip id="veh0" depart="0.00" departLane="best" from="26119992#8" to="-207634523#0" type="veh_passenger"/>
    <trip id="veh1" depart="4.61" departLane="best" from="112465240#3" to="128363659#0" type="veh_passenger"/>
    <trip id="veh2" depart="9.22" departLane="best" from="34607518#7" to="332479850#0" type="veh_passenger"/>
    <trip id="veh3" depart="13.83" departLane="best" from="452076637#3" to="-262474849#2" type="veh_passenger"/>
    <trip id="veh4" depart="18.44" departLane="best" from="14333465#1" to="-210365858#0" type="veh_passenger"/>
    <trip id="veh5" depart="23.06" departLane="best" from="-39888370" to="233098267" type="veh_passenger"/>
    <trip id="veh6" depart="27.67" departLane="best" from="-146190183#0" to="124539828#1" type="veh_passenger"/>
    <trip id="veh7" depart="32.28" departLane="best" from="262474849#1" to="258853581#4" type="veh_passenger"/>
    <trip id="veh9" depart="41.50" departLane="best" from="39671211" to="-13277357#0" type="veh_passenger"/>
    <trip id="veh10" depart="46.11" departLane="best" from="13848688#1" to="-434878401#1" type="veh_passenger"/>
    <trip id="veh11" depart="50.72" departLane="best" from="608420970#0" to="14333888#6" type="veh_passenger"/>
    <trip id="veh13" depart="59.94" departLane="best" departSpeed="max" from="39896043" to="262579556#1" type="veh_passenger"/>
    <trip id="veh15" depart="69.17" departLane="best" from="216969809#5" to="8367054" type="veh_passenger"/>
    <trip id="veh17" depart="78.39" departLane="best" from="434878401#1" to="26119992#8" type="veh_passenger"/>
    <trip id="veh18" depart="83.00" departLane="best" from="307804461#2" to="-252518642#1" type="veh_passenger"/>
    <trip id="veh19" depart="87.61" departLane="best" departSpeed="max" from="-39896053" to="14326558#0" type="veh_passenger"/>
    <trip id="veh20" depart="92.22" departLane="best" from="-252518642#1" to="128825638#2" type="veh_passenger"/>
    <trip id="veh21" depart="96.83" departLane="best" from="-26119992#3" to="14326464#7" type="veh_passenger"/>
    <trip id="veh22" depart="101.44" departLane="best" from="26119992#6" to="167487364" type="veh_passenger"/>
    <trip id="veh23" depart="106.05" departLane="best" from="14326558#0" to="128363657" type="veh_passenger"/>
    <trip id="veh24" depart="110.67" departLane="best" departSpeed="max" from="-96151239#3" to="60175941#0" type="veh_passenger"/>
    <trip id="veh25" depart="115.28" departLane="best" departSpeed="max" from="26207794#0" to="262945890#0" type="veh_passenger"/>
    <trip id="veh26" depart="119.89" departLane="best" departSpeed="max" from="-386286205" to="38336628#2" type="veh_passenger"/>
    <trip id="veh27" depart="124.50" departLane="best" departSpeed="max" from="-36748083#3" to="197464424#1" type="veh_passenger"/>
    <trip id="veh28" depart="129.11" departLane="best" from="8367098#1" to="292119381" type="veh_passenger"/>
    <trip id="veh29" depart="133.72" departLane="best" from="227888631#1" to="332479850#4" type="veh_passenger"/>
    <trip id="veh30" depart="138.33" departLane="best" from="39895304#1" to="39670508#0-AddedOnRampEdge" type="veh_passenger"/>
    <trip id="veh31" depart="142.94" departLane="best" departSpeed="max" from="-39896053" to="-210365858#2" type="veh_passenger"/>
    <trip id="veh33" depart="152.17" departLane="best" departSpeed="max" from="-39888043#1" to="60175941#3" type="veh_passenger"/>
    <trip id="veh35" depart="161.39" departLane="best" from="262474849#5" to="207634492" type="veh_passenger"/>
    <trip id="veh36" depart="166.00" departLane="best" from="484592257#0" to="216159806#1" type="veh_passenger"/>
    <trip id="veh37" depart="170.61" departLane="best" from="-8367089#1" to="13277357#4" type="veh_passenger"/>
    <trip id="veh38" depart="175.22" departLane="best" from="229802211" to="13836129#0" type="veh_passenger"/>
    <trip id="veh39" depart="179.83" departLane="best" from="255848372" to="482296561" type="veh_passenger"/>
    <trip id="veh40" depart="184.44" departLane="best" departSpeed="max" from="14327868#0" to="128363658#1" type="veh_passenger"/>
    <trip id="veh43" depart="198.28" departLane="best" from="-26119992#9" to="28193999#1" type="veh_passenger"/>
    <trip id="veh44" depart="202.89" departLane="best" departSpeed="max" from="39658536#0" to="210336697" type="veh_passenger"/>
    <trip id="veh45" depart="207.50" departLane="best" departSpeed="max" from="-216891254#1" to="206720845#0" type="veh_passenger"/>
    <trip id="veh47" depart="216.72" departLane="best" from="608421700#2-AddedOffRampEdge" to="434879926#2" type="veh_passenger"/>
    <trip id="veh50" depart="230.55" departLane="best" departSpeed="max" from="-96151239#3" to="292119381" type="veh_passenger"/>
    <trip id="veh52" depart="239.78" departLane="best" from="167487364" to="608420970#2" type="veh_passenger"/>
    <trip id="veh53" depart="244.39" departLane="best" from="448850568#0" to="13836129#2" type="veh_passenger"/>
    <trip id="veh54" depart="249.00" departLane="best" from="210851328#2" to="-8367089#1" type="veh_passenger"/>
    <trip id="veh56" depart="258.22" departLane="best" from="128363659#1" to="287648900" type="veh_passenger"/>
    <trip id="veh57" depart="262.83" departLane="best" departSpeed="max" from="38336627#0" to="258853579#0" type="veh_passenger"/>
    <trip id="veh58" depart="267.44" departLane="best" from="38336628#4" to="256431162#1" type="veh_passenger"/>
    <trip id="veh59" depart="272.05" departLane="best" from="-13277357#3" to="60175223#2" type="veh_passenger"/>
    <trip id="veh60" depart="276.67" departLane="best" from="448850570#2" to="39896053" type="veh_passenger"/>
    <trip id="veh61" depart="281.28" departLane="best" from="128825638#4" to="-256431162#0" type="veh_passenger"/>
    <trip id="veh62" depart="285.89" departLane="best" from="448850570#2" to="60175941#7" type="veh_passenger"/>
    <trip id="veh63" depart="290.50" departLane="best" from="-255848372" to="220232893#1" type="veh_passenger"/>
    <trip id="veh64" depart="295.11" departLane="best" from="206720845#1" to="26119844#1" type="veh_passenger"/>
    <trip id="veh65" depart="299.72" departLane="best" from="-8367089#1" to="448850570#8" type="veh_passenger"/>
    <trip id="veh66" depart="304.33" departLane="best" from="14333474" to="128363657" type="veh_passenger"/>
    <trip id="veh68" depart="313.55" departLane="best" from="8367104#8" to="304684297#1" type="veh_passenger"/>
    <trip id="veh69" depart="318.16" departLane="best" from="-262474849#1" to="128363659#1" type="veh_passenger"/>
    <trip id="veh71" depart="327.39" departLane="best" from="-434860177#0" to="128363658#1" type="veh_passenger"/>
    <trip id="veh72" depart="332.00" departLane="best" departSpeed="max" from="-39896053" to="484592257#0" type="veh_passenger"/>
    <trip id="veh73" depart="336.61" departLane="best" from="434878400#0" to="-26119992#3" type="veh_passenger"/>
    <trip id="veh74" depart="341.22" departLane="best" from="-434879926#1" to="31573135#2" type="veh_passenger"/>
    <trip id="veh75" depart="345.83" departLane="best" from="-39888049" to="-39678582#4" type="veh_passenger"/>
    <trip id="veh76" depart="350.44" departLane="best" from="59525260#2" to="26119992#4" type="veh_passenger"/>
    <trip id="veh77" depart="355.05" departLane="best" from="200967938" to="39678582#3" type="veh_passenger"/>
    <trip id="veh78" depart="359.66" departLane="best" from="-26119992#11" to="210841125#0" type="veh_passenger"/>
    <trip id="veh79" depart="364.28" departLane="best" from="14333500#0" to="216969809#3" type="veh_passenger"/>
    <trip id="veh80" depart="368.89" departLane="best" departSpeed="max" from="34607518#0" to="332053082#2" type="veh_passenger"/>
    <trip id="veh81" depart="373.50" departLane="best" from="8367070#0" to="-280786930#0" type="veh_passenger"/>
    <trip id="veh82" depart="378.11" departLane="best" from="14327868#2" to="156211618#0" type="veh_passenger"/>
    <trip id="veh83" depart="382.72" departLane="best" from="434878401#1" to="13277357#5" type="veh_passenger"/>
    <trip id="veh84" depart="387.33" departLane="best" from="-484592257#1" to="595164143#4" type="veh_passenger"/>
    <trip id="veh85" depart="391.94" departLane="best" from="167487357#0" to="448850568#0" type="veh_passenger"/>
    <trip id="veh86" depart="396.55" departLane="best" from="218020117" to="-255778743#0" type="veh_passenger"/>
    <trip id="veh87" depart="401.16" departLane="best" from="608421700#1" to="59525260#1" type="veh_passenger"/>
    <trip id="veh88" depart="405.78" departLane="best" from="434860177#0" to="-484592257#0" type="veh_passenger"/>
    <trip id="veh89" depart="410.39" departLane="best" from="207724051#0" to="128363657" type="veh_passenger"/>
    <trip id="veh90" depart="415.00" departLane="best" departSpeed="max" from="14327868#0" to="-256431162#0" type="veh_passenger"/>
    <trip id="veh91" depart="419.61" departLane="best" from="14326558#4" to="8367104#4" type="veh_passenger"/>
    <trip id="veh92" depart="424.22" departLane="best" departSpeed="max" from="-96151239#3" to="39671211" type="veh_passenger"/>
    <trip id="veh93" depart="428.83" departLane="best" from="167487526" to="210336698" type="veh_passenger"/>
    <trip id="veh94" depart="433.44" departLane="best" from="608420970#0" to="95841157" type="veh_passenger"/>
    <trip id="veh95" depart="438.05" departLane="best" from="226624856" to="374346169" type="veh_passenger"/>
    <trip id="veh96" depart="442.66" departLane="best" departSpeed="max" from="-34683151#1" to="14326558#3" type="veh_passenger"/>
    <trip id="veh97" depart="447.28" departLane="best" from="608421700#1" to="26119992#9" type="veh_passenger"/>
    <trip id="veh98" depart="451.89" departLane="best" from="216972581#3" to="386286210" type="veh_passenger"/>
    <trip id="veh100" depart="461.11" departLane="best" departSpeed="max" from="211314340#0" to="434878401#3" type="veh_passenger"/>
    <trip id="veh101" depart="465.72" departLane="best" departSpeed="max" from="-34683151#1" to="608421700#1" type="veh_passenger"/>
    <trip id="veh102" depart="470.33" departLane="best" from="-252518642#1" to="112465243#0" type="veh_passenger"/>
    <trip id="veh103" depart="474.94" departLane="best" from="-434878401#3" to="-36748084#2" type="veh_passenger"/>
    <trip id="veh106" depart="488.78" departLane="best" from="215210562#2" to="60175590#3" type="veh_passenger"/>
    <trip id="veh107" depart="493.39" departLane="best" from="-434879926#2" to="207634492" type="veh_passenger"/>
    <trip id="veh108" depart="498.00" departLane="best" from="262945890#5" to="14326558#4" type="veh_passenger"/>
    <trip id="veh109" depart="502.61" departLane="best" from="13277357#3" to="39658536#1" type="veh_passenger"/>
    <trip id="veh110" depart="507.22" departLane="best" departSpeed="max" from="-233007929" to="216159806#0" type="veh_passenger"/>
    <trip id="veh112" depart="516.44" departLane="best" departSpeed="max" from="-233007929" to="128363657" type="veh_passenger"/>
    <trip id="veh113" depart="521.05" departLane="best" departSpeed="max" from="-96151239#3" to="60175590#2" type="veh_passenger"/>
    <trip id="veh114" depart="525.66" departLane="best" from="448850570#6" to="452076637#3" type="veh_passenger"/>
    <trip id="veh115" depart="530.27" departLane="best" from="14326493#4" to="-434878401#4" type="veh_passenger"/>
    <trip id="veh116" depart="534.89" departLane="best" from="39894728#2" to="346992934#6" type="veh_passenger"/>
    <trip id="veh117" depart="539.50" departLane="best" from="26119844#0" to="8367104#8" type="veh_passenger"/>
    <trip id="veh118" depart="544.11" departLane="best" from="262474849#4" to="-13277357#1" type="veh_passenger"/>
    <trip id="veh119" depart="548.72" departLane="best" from="39888043#0" to="14326558#4" type="veh_passenger"/>
    <trip id="veh120" depart="553.33" departLane="best" from="262616020#0" to="60175941#2" type="veh_passenger"/>
    <trip id="veh121" depart="557.94" departLane="best" departSpeed="max" from="-278570718#3" to="-349620091" type="veh_passenger"/>
    <trip id="veh122" depart="562.55" departLane="best" from="-26119992#7" to="26119880" type="veh_passenger"/>
    <trip id="veh123" depart="567.16" departLane="best" from="112465240#2" to="262579556#2" type="veh_passenger"/>
    <trip id="veh124" depart="571.77" departLane="best" from="332053082#3" to="128362570#3" type="veh_passenger"/>
    <trip id="veh125" depart="576.39" departLane="best" from="26119992#5" to="13836129#2" type="veh_passenger"/>
    <trip id="veh126" depart="581.00" departLane="best" from="208580373#1" to="484592257#0" type="veh_passenger"/>
    <trip id="veh127" depart="585.61" departLane="best" departSpeed="max" from="39896043" to="-262474849#7" type="veh_passenger"/>
    <trip id="veh128" depart="590.22" departLane="best" from="-128362570#2" to="39670422#2" type="veh_passenger"/>
    <trip id="veh129" depart="594.83" departLane="best" from="26119992#6" to="13836129#0" type="veh_passenger"/>
    <trip id="veh130" depart="599.44" departLane="best" from="346992934#1" to="26119844#2" type="veh_passenger"/>
    <trip id="veh131" depart="604.05" departLane="best" from="14333500#5" to="-13277357#2" type="veh_passenger"/>
    <trip id="veh133" depart="613.27" departLane="best" from="482276569#1" to="259888928#0" type="veh_passenger"/>
    <trip id="veh135" depart="622.50" departLane="best" departSpeed="max" from="-287648900" to="-39658536#0" type="veh_passenger"/>
    <trip id="veh136" depart="627.11" departLane="best" from="128825640#0" to="482296562" type="veh_passenger"/>
    <trip id="veh137" depart="631.72" departLane="best" from="39668434#1" to="434879926#2" type="veh_passenger"/>
    <trip id="veh138" depart="636.33" departLane="best" from="482264025#1" to="128363657" type="veh_passenger"/>
    <trip id="veh139" depart="640.94" departLane="best" from="-484592257#1" to="-28193999#2" type="veh_passenger"/>
    <trip id="veh140" depart="645.55" departLane="best" from="38336628#5" to="482261339#0" type="veh_passenger"/>
    <trip id="veh141" depart="650.16" departLane="best" departSpeed="max" from="14328446#0" to="280786930#1" type="veh_passenger"/>
    <trip id="veh142" depart="654.77" departLane="best" departSpeed="max" from="-34683151#1" to="60175224#2" type="veh_passenger"/>
    <trip id="veh143" depart="659.39" departLane="best" from="434878401#2" to="8367070#0" type="veh_passenger"/>
    <trip id="veh144" depart="664.00" departLane="best" from="39678582#3" to="482240915#1" type="veh_passenger"/>
    <trip id="veh145" depart="668.61" departLane="best" from="-14333888#3" to="38336628#5" type="veh_passenger"/>
    <trip id="veh146" depart="673.22" departLane="best" departSpeed="max" from="13848688#0" to="60175590#0" type="veh_passenger"/>
    <trip id="veh147" depart="677.83" departLane="best" from="39669380" to="448850570#1" type="veh_passenger"/>
    <trip id="veh149" depart="687.05" departLane="best" from="174689857" to="14326572#3" type="veh_passenger"/>
    <trip id="veh150" depart="691.66" departLane="best" from="39668434#0" to="128823187#1" type="veh_passenger"/>
    <trip id="veh151" depart="696.27" departLane="best" from="-14333888#1" to="112635323#0" type="veh_passenger"/>
    <trip id="veh152" depart="700.89" departLane="best" from="13836129#0" to="448850570#1" type="veh_passenger"/>
    <trip id="veh153" depart="705.50" departLane="best" from="26119992#9" to="207634492" type="veh_passenger"/>
    <trip id="veh155" depart="714.72" departLane="best" from="60175590#0" to="-349620091" type="veh_passenger"/>
    <trip id="veh156" depart="719.33" departLane="best" from="608421700#2-AddedOffRampEdge" to="-8367089#1" type="veh_passenger"/>
    <trip id="veh161" depart="742.38" departLane="best" from="14326572#2" to="26119992#8" type="veh_passenger"/>
    <trip id="veh162" depart="747.00" departLane="best" from="-551619530#0" to="36740122" type="veh_passenger"/>
    <trip id="veh163" depart="751.61" departLane="best" from="-128362570#0" to="59525257#2" type="veh_passenger"/>
    <trip id="veh164" depart="756.22" departLane="best" from="216972581#0" to="374346173" type="veh_passenger"/>
    <trip id="veh165" depart="760.83" departLane="best" from="346992934#2" to="332053082#0" type="veh_passenger"/>
    <trip id="veh166" depart="765.44" departLane="best" from="14326493#2" to="-26119992#2" type="veh_passenger"/>
    <trip id="veh167" depart="770.05" departLane="best" from="262616020#1" to="14333500#3" type="veh_passenger"/>
    <trip id="veh168" depart="774.66" departLane="best" from="13277357#2" to="434878401#0" type="veh_passenger"/>
    <trip id="veh169" depart="779.27" departLane="best" from="332479850#0" to="14326572#0" type="veh_passenger"/>
    <trip id="veh170" depart="783.88" departLane="best" from="128825640#1" to="207724055" type="veh_passenger"/>
    <trip id="veh171" depart="788.50" departLane="best" from="14327868#2" to="14326558#3" type="veh_passenger"/>
    <trip id="veh172" depart="793.11" departLane="best" from="-262474849#5" to="210328137" type="veh_passenger"/>
    <trip id="veh173" depart="797.72" departLane="best" from="60175590#1" to="332479850#0" type="veh_passenger"/>
    <trip id="veh174" depart="802.33" departLane="best" from="482276569#0" to="275860210" type="veh_passenger"/>
    <trip id="veh175" depart="806.94" departLane="best" from="128823187#0" to="259888928#2" type="veh_passenger"/>
    <trip id="veh176" depart="811.55" departLane="best" from="-12298717" to="14326493#4" type="veh_passenger"/>
    <trip id="veh177" depart="816.16" departLane="best" from="262474849#5" to="216891254#0" type="veh_passenger"/>
    <trip id="veh178" depart="820.77" departLane="best" from="167487357#0" to="128363657" type="veh_passenger"/>
    <trip id="veh179" depart="825.38" departLane="best" from="206720845#0" to="482296563#0" type="veh_passenger"/>
    <trip id="veh180" depart="830.00" departLane="best" from="39668434#1" to="-548373860" type="veh_passenger"/>
    <trip id="veh181" depart="834.61" departLane="best" from="-255778743#3" to="252518644#0" type="veh_passenger"/>
    <trip id="veh182" depart="839.22" departLane="best" from="26119992#4" to="14333888#3" type="veh_passenger"/>
    <trip id="veh183" depart="843.83" departLane="best" from="39888045#1" to="394998026#3" type="veh_passenger"/>
    <trip id="veh184" depart="848.44" departLane="best" from="27149319#1" to="128363659#1" type="veh_passenger"/>
    <trip id="veh185" depart="853.05" departLane="best" departSpeed="max" from="-39690472" to="-200072875" type="veh_passenger"/>
    <trip id="veh186" depart="857.66" departLane="best" from="-482261338#1" to="216972581#3" type="veh_passenger"/>
    <trip id="veh187" depart="862.27" departLane="best" from="434860177#0" to="-26119992#4" type="veh_passenger"/>
    <trip id="veh188" depart="866.88" departLane="best" from="14328446#5" to="287648900" type="veh_passenger"/>
    <trip id="veh189" depart="871.50" departLane="best" departSpeed="max" from="210365858#0" to="13277357#2" type="veh_passenger"/>
    <trip id="veh190" depart="876.11" departLane="best" from="262474849#6" to="-128825640#0" type="veh_passenger"/>
    <trip id="veh191" depart="880.72" departLane="best" from="349620090#3" to="39670422#1" type="veh_passenger"/>
    <trip id="veh192" depart="885.33" departLane="best" from="-26119992#7" to="210339821#1" type="veh_passenger"/>
    <trip id="veh193" depart="889.94" departLane="best" departSpeed="max" from="-386286206#1" to="608420973" type="veh_passenger"/>
    <trip id="veh194" depart="894.55" departLane="best" from="215200349#1" to="-255778743#0" type="veh_passenger"/>
    <trip id="veh195" depart="899.16" departLane="best" from="-484592257#1" to="434878401#0" type="veh_passenger"/>
    <trip id="veh196" depart="903.77" departLane="best" departSpeed="max" from="174689856" to="39888043#1" type="veh_passenger"/>
    <trip id="veh197" depart="908.38" departLane="best" from="262945890#0" to="8367114#0" type="veh_passenger"/>
    <trip id="veh198" depart="912.99" departLane="best" departSpeed="max" from="256431162#0" to="608420970#0" type="veh_passenger"/>
    <trip id="veh199" depart="917.61" departLane="best" from="452076637#0" to="262945890#4" type="veh_passenger"/>
    <trip id="veh200" depart="922.22" departLane="best" from="332479850#0" to="233098267" type="veh_passenger"/>
    <trip id="veh201" depart="926.83" departLane="best" from="39894728#0" to="259888928#2" type="veh_passenger"/>
    <trip id="veh202" depart="931.44" departLane="best" from="482261339#0" to="386286206#1" type="veh_passenger"/>
    <trip id="veh203" depart="936.05" departLane="best" from="206720845#1" to="13801868#1" type="veh_passenger"/>
    <trip id="veh204" depart="940.66" departLane="best" from="-482296560#1" to="287648900" type="veh_passenger"/>
    <trip id="veh205" depart="945.27" departLane="best" from="38336627#1" to="255848372" type="veh_passenger"/>
    <trip id="veh206" depart="949.88" departLane="best" from="26119992#10" to="14326464#4" type="veh_passenger"/>
    <trip id="veh207" depart="954.49" departLane="best" from="-239593895#1" to="14326493#3" type="veh_passenger"/>
    <trip id="veh209" depart="963.72" departLane="best" from="216972581#1" to="-39888045#1" type="veh_passenger"/>
    <trip id="veh210" depart="968.33" departLane="best" from="-434860177#0" to="34683151#0" type="veh_passenger"/>
    <trip id="veh211" depart="972.94" departLane="best" from="307804461#3" to="-26119992#0" type="veh_passenger"/>
    <trip id="veh212" depart="977.55" departLane="best" departSpeed="max" from="14328446#0" to="258853581#3" type="veh_passenger"/>
    <trip id="veh213" depart="982.16" departLane="best" from="14328446#5" to="128363657" type="veh_passenger"/>
    <trip id="veh214" depart="986.77" departLane="best" from="14333321#2" to="484592256#3" type="veh_passenger"/>
    <trip id="veh215" depart="991.38" departLane="best" from="255778743#3" to="34683151#0" type="veh_passenger"/>
    <trip id="veh216" depart="995.99" departLane="best" from="434872534#5" to="39669069#2" type="veh_passenger"/>
    <trip id="veh217" depart="1000.61" departLane="best" from="14326558#4" to="-128825640#0" type="veh_passenger"/>
    <trip id="veh218" depart="1005.22" departLane="best" from="142214763#1" to="39658536#2" type="veh_passenger"/>
    <trip id="veh219" depart="1009.83" departLane="best" from="434872534#2" to="608420970#2" type="veh_passenger"/>
    <trip id="veh220" depart="1014.44" departLane="best" from="216972801#1" to="262474849#9" type="veh_passenger"/>
    <trip id="veh221" depart="1019.05" departLane="best" from="-39888372#1" to="128363658#1" type="veh_passenger"/>
    <trip id="veh222" depart="1023.66" departLane="best" from="156211618#0" to="-210365858#0" type="veh_passenger"/>
    <trip id="veh223" depart="1028.27" departLane="best" departSpeed="max" from="13848688#0" to="332479850#1" type="veh_passenger"/>
    <trip id="veh224" depart="1032.88" departLane="best" departSpeed="max" from="14328446#0" to="-482296560#1" type="veh_passenger"/>
    <trip id="veh225" depart="1037.49" departLane="best" from="190128490" to="-39658536#0" type="veh_passenger"/>
    <trip id="veh226" depart="1042.11" departLane="best" from="26119900#1" to="-210339821#0" type="veh_passenger"/>
    <trip id="veh227" depart="1046.72" departLane="best" departSpeed="max" from="14327351#0" to="26119992#10" type="veh_passenger"/>
    <trip id="veh228" depart="1051.33" departLane="best" from="-146190183#1" to="30405557#0" type="veh_passenger"/>
    <trip id="veh229" depart="1055.94" departLane="best" departSpeed="max" from="-278570718#3" to="216891254#0" type="veh_passenger"/>
    <trip id="veh231" depart="1065.16" departLane="best" departSpeed="max" from="-39888043#1" to="14333474" type="veh_passenger"/>
    <trip id="veh232" depart="1069.77" departLane="best" from="374346173" to="197464424#1" type="veh_passenger"/>
    <trip id="veh233" depart="1074.38" departLane="best" from="349620091" to="39896053" type="veh_passenger"/>
    <trip id="veh234" depart="1078.99" departLane="best" departSpeed="max" from="-548373865" to="-262474849#0" type="veh_passenger"/>
    <trip id="veh235" depart="1083.61" departLane="best" from="-13277357#3" to="258853579#0" type="veh_passenger"/>
    <trip id="veh236" depart="1088.22" departLane="best" from="95841157" to="167057944#0" type="veh_passenger"/>
    <trip id="veh237" depart="1092.83" departLane="best" from="262474849#1" to="39670518#3" type="veh_passenger"/>
    <trip id="veh238" depart="1097.44" departLane="best" from="262474849#2" to="39658536#2" type="veh_passenger"/>
    <trip id="veh239" depart="1102.05" departLane="best" from="60175941#3" to="124539828#1" type="veh_passenger"/>
    <trip id="veh240" depart="1106.66" departLane="best" from="-13277357#4" to="-434860177#0" type="veh_passenger"/>
    <trip id="veh241" depart="1111.27" departLane="best" from="-262474849#5" to="31573135#2" type="veh_passenger"/>
    <trip id="veh242" depart="1115.88" departLane="best" from="233006425#0" to="128363658#1" type="veh_passenger"/>
    <trip id="veh243" depart="1120.49" departLane="best" from="304688480#2" to="39669178#1" type="veh_passenger"/>
    <trip id="veh244" depart="1125.10" departLane="best" from="39888049" to="608421700#3" type="veh_passenger"/>
    <trip id="veh245" depart="1129.72" departLane="best" from="608420970#0" to="207634492" type="veh_passenger"/>
    <trip id="veh246" depart="1134.33" departLane="best" from="332053082#2" to="-26119992#6" type="veh_passenger"/>
    <trip id="veh247" depart="1138.94" departLane="best" departSpeed="max" from="30405423" to="28193999#1" type="veh_passenger"/>
    <trip id="veh248" depart="1143.55" departLane="best" from="-26119992#4" to="39670422#2" type="veh_passenger"/>
    <trip id="veh249" depart="1148.16" departLane="best" from="434860177#1" to="262474849#8" type="veh_passenger"/>
    <trip id="veh250" depart="1152.77" departLane="best" from="-262474849#1" to="8367104#2" type="veh_passenger"/>
    <trip id="veh251" depart="1157.38" departLane="best" from="38336628#5" to="157156090#2" type="veh_passenger"/>
    <trip id="veh252" depart="1161.99" departLane="best" from="14333733#0" to="190128487#3" type="veh_passenger"/>
    <trip id="veh253" depart="1166.60" departLane="best" departSpeed="max" from="211314340#0" to="156211619" type="veh_passenger"/>
    <trip id="veh254" depart="1171.22" departLane="best" from="434860177#0" to="39894728#3" type="veh_passenger"/>
    <trip id="veh255" depart="1175.83" departLane="best" from="-26119992#6" to="608421700#1" type="veh_passenger"/>
    <trip id="veh256" depart="1180.44" departLane="best" from="30912936" to="211436103#0" type="veh_passenger"/>
    <trip id="veh257" depart="1185.05" departLane="best" from="34607518#3" to="608421700#5" type="veh_passenger"/>
    <trip id="veh259" depart="1194.27" departLane="best" from="156211618#0" to="38336628#4" type="veh_passenger"/>
    <trip id="veh260" depart="1198.88" departLane="best" departSpeed="max" from="-96151239#3" to="434878401#3" type="veh_passenger"/>
    <trip id="veh261" depart="1203.49" departLane="best" from="39894728#0" to="-262474849#2" type="veh_passenger"/>
    <trip id="veh262" depart="1208.10" departLane="best" from="448850570#6" to="13277357#2" type="veh_passenger"/>
    <trip id="veh263" depart="1212.72" departLane="best" from="190128487#4" to="262945890#1" type="veh_passenger"/>
    <trip id="veh264" depart="1217.33" departLane="best" from="434860177#1" to="112465240#1" type="veh_passenger"/>
    <trip id="veh265" depart="1221.94" departLane="best" departSpeed="max" from="-39888043#1" to="39862802" type="veh_passenger"/>
    <trip id="veh266" depart="1226.55" departLane="best" departSpeed="max" from="-128363658#1" to="608420970#0" type="veh_passenger"/>
    <trip id="veh268" depart="1235.77" departLane="best" from="208580373#1" to="39668434#0" type="veh_passenger"/>
    <trip id="veh269" depart="1240.38" departLane="best" departSpeed="max" from="30405423" to="304680071" type="veh_passenger"/>
    <trip id="veh271" depart="1249.60" departLane="best" from="304680071" to="14326572#3" type="veh_passenger"/>
    <trip id="veh272" depart="1254.22" departLane="best" departSpeed="max" from="255778743#0" to="216972581#1" type="veh_passenger"/>
    <trip id="veh273" depart="1258.83" departLane="best" from="216159806#1" to="210339821#1" type="veh_passenger"/>
    <trip id="veh274" depart="1263.44" departLane="best" from="346992934#7" to="14333500#4" type="veh_passenger"/>
    <trip id="veh275" depart="1268.05" departLane="best" from="307804461#1" to="14326464#2" type="veh_passenger"/>
    <trip id="veh276" depart="1272.66" departLane="best" departSpeed="max" from="-548373865" to="-386286206#0" type="veh_passenger"/>
    <trip id="veh277" depart="1277.27" departLane="best" departSpeed="max" from="-39669069#2" to="-36748084#2" type="veh_passenger"/>
    <trip id="veh278" depart="1281.88" departLane="best" from="216969809#5" to="39668885#2" type="veh_passenger"/>
    <trip id="veh279" depart="1286.49" departLane="best" departSpeed="max" from="-39658536#2" to="128363658#1" type="veh_passenger"/>
    <trip id="veh280" depart="1291.10" departLane="best" from="207634523#0" to="38336628#1" type="veh_passenger"/>
    <trip id="veh281" depart="1295.72" departLane="best" from="8366889#1" to="256249046#2" type="veh_passenger"/>
    <trip id="veh282" depart="1300.33" departLane="best" from="124539825" to="-28193999#0" type="veh_passenger"/>
    <trip id="veh283" depart="1304.94" departLane="best" departSpeed="max" from="-39669069#2" to="128823187#1" type="veh_passenger"/>
    <trip id="veh284" depart="1309.55" departLane="best" from="-394998026#1" to="-13277357#5" type="veh_passenger"/>
    <trip id="veh285" depart="1314.16" departLane="best" from="643548708" to="26119880" type="veh_passenger"/>
    <trip id="veh286" depart="1318.77" departLane="best" from="304688479" to="-39658536#0" type="veh_passenger"/>
    <trip id="veh287" depart="1323.38" departLane="best" from="434879926#2" to="26119992#6" type="veh_passenger"/>
    <trip id="veh288" depart="1327.99" departLane="best" from="197434949#1" to="212706766#0" type="veh_passenger"/>
    <trip id="veh289" depart="1332.60" departLane="best" departSpeed="max" from="-39658536#2" to="-255778743#0" type="veh_passenger"/>
    <trip id="veh290" depart="1337.21" departLane="best" from="60175590#1" to="216972801#0" type="veh_passenger"/>
    <trip id="veh291" depart="1341.83" departLane="best" from="39888368#3" to="207634492" type="veh_passenger"/>
    <trip id="veh292" depart="1346.44" departLane="best" departSpeed="max" from="-233007929" to="287648900" type="veh_passenger"/>
    <trip id="veh294" depart="1355.66" departLane="best" from="229818921" to="14326572#2" type="veh_passenger"/>
    <trip id="veh295" depart="1360.27" departLane="best" from="8367104#7" to="-36748084#0" type="veh_passenger"/>
    <trip id="veh296" depart="1364.88" departLane="best" departSpeed="max" from="38336627#0" to="262616020#1" type="veh_passenger"/>
    <trip id="veh297" depart="1369.49" departLane="best" departSpeed="max" from="39658536#0" to="128363661" type="veh_passenger"/>
    <trip id="veh298" depart="1374.10" departLane="best" from="167487357#0" to="434879926#2" type="veh_passenger"/>
    <trip id="veh299" depart="1378.71" departLane="best" from="26119900#0" to="262945890#0" type="veh_passenger"/>
    <trip id="veh300" depart="1383.33" departLane="best" from="34683791" to="60175941#7" type="veh_passenger"/>
    <trip id="veh301" depart="1387.94" departLane="best" departSpeed="max" from="-39865747" to="128363657" type="veh_passenger"/>
    <trip id="veh302" depart="1392.55" departLane="best" from="262474849#9" to="-434878401#3" type="veh_passenger"/>
    <trip id="veh303" depart="1397.16" departLane="best" departSpeed="max" from="-386286206#1" to="-26119992#6" type="veh_passenger"/>
    <trip id="veh304" depart="1401.77" departLane="best" from="-128362570#1" to="215210562#1" type="veh_passenger"/>
    <trip id="veh305" depart="1406.38" departLane="best" departSpeed="max" from="256431162#0" to="14326558#1" type="veh_passenger"/>
    <trip id="veh306" depart="1410.99" departLane="best" from="-434860177#1" to="35203817#0" type="veh_passenger"/>
    <trip id="veh307" depart="1415.60" departLane="best" from="307804461#1" to="215301977#0" type="veh_passenger"/>
    <trip id="veh308" depart="1420.21" departLane="best" from="292119381" to="59525257#0" type="veh_passenger"/>
    <trip id="veh309" depart="1424.83" departLane="best" from="394998026#2" to="28193999#0" type="veh_passenger"/>
    <trip id="veh310" depart="1429.44" departLane="best" from="262474849#9" to="60175590#2" type="veh_passenger"/>
    <trip id="veh311" depart="1434.05" departLane="best" from="14333500#2" to="258853581#4" type="veh_passenger"/>
    <trip id="veh312" depart="1438.66" departLane="best" departSpeed="max" from="26207794#0" to="51230332#0" type="veh_passenger"/>
    <trip id="veh313" depart="1443.27" departLane="best" from="39888372#3" to="-26119992#3" type="veh_passenger"/>
    <trip id="veh314" depart="1447.88" departLane="best" departSpeed="max" from="-36748083#3" to="14326572#3" type="veh_passenger"/>
    <trip id="veh315" depart="1452.49" departLane="best" departSpeed="max" from="349620090#0" to="26119992#3" type="veh_passenger"/>
    <trip id="veh317" depart="1461.71" departLane="best" departSpeed="max" from="30405423" to="346992934#1" type="veh_passenger"/>
    <trip id="veh318" depart="1466.33" departLane="best" from="60175590#2" to="233007929" type="veh_passenger"/>
    <trip id="veh319" depart="1470.94" departLane="best" departSpeed="max" from="210365858#0" to="-26119992#9" type="veh_passenger"/>
    <trip id="veh322" depart="1484.77" departLane="best" from="39894728#3" to="26119992#7" type="veh_passenger"/>
    <trip id="veh323" depart="1489.38" departLane="best" from="60175941#3" to="96151239#0" type="veh_passenger"/>
    <trip id="veh326" depart="1503.21" departLane="best" from="197464424#1" to="304688479" type="veh_passenger"/>
    <trip id="veh327" depart="1507.82" departLane="best" from="501277146#0" to="112465240#1" type="veh_passenger"/>
    <trip id="veh328" depart="1512.44" departLane="best" from="256165013" to="287648900" type="veh_passenger"/>
    <trip id="veh330" depart="1521.66" departLane="best" departSpeed="max" from="142214759#0" to="14333733#1" type="veh_passenger"/>
    <trip id="veh331" depart="1526.27" departLane="best" from="262945890#3" to="434879926#1" type="veh_passenger"/>
    <trip id="veh332" depart="1530.88" departLane="best" from="13836129#2" to="34683151#0" type="veh_passenger"/>
    <trip id="veh334" depart="1540.10" departLane="best" from="39862487#0" to="26119844#1" type="veh_passenger"/>
    <trip id="veh336" depart="1549.32" departLane="best" from="13801868#0" to="8366893#1" type="veh_passenger"/>
    <trip id="veh337" depart="1553.94" departLane="best" departSpeed="max" from="14328446#0" to="252518642#1" type="veh_passenger"/>
    <trip id="veh338" depart="1558.55" departLane="best" from="8367089#1" to="307804461#1" type="veh_passenger"/>
    <trip id="veh339" depart="1563.16" departLane="best" from="216972581#3" to="210328137" type="veh_passenger"/>
    <trip id="veh340" depart="1567.77" departLane="best" departSpeed="max" from="-39668885#2" to="167487363#1" type="veh_passenger"/>
    <trip id="veh341" depart="1572.38" departLane="best" from="36748084#2" to="28193999#0" type="veh_passenger"/>
    <trip id="veh342" depart="1576.99" departLane="best" from="374346169" to="128362570#3" type="veh_passenger"/>
    <trip id="veh343" depart="1581.60" departLane="best" from="217628815" to="59525260#2" type="veh_passenger"/>
    <trip id="veh344" depart="1586.21" departLane="best" from="156211619" to="34683791" type="veh_passenger"/>
    <trip id="veh345" depart="1590.82" departLane="best" from="-262474849#1" to="8367054" type="veh_passenger"/>
    <trip id="veh346" depart="1595.44" departLane="best" from="259888928#0" to="128825641#1" type="veh_passenger"/>
    <trip id="veh347" depart="1600.05" departLane="best" from="-349620089" to="26119844#1" type="veh_passenger"/>
    <trip id="veh348" depart="1604.66" departLane="best" from="220232893#1" to="-262474849#7" type="veh_passenger"/>
    <trip id="veh349" depart="1609.27" departLane="best" from="8367104#2" to="551619530#0" type="veh_passenger"/>
    <trip id="veh350" depart="1613.88" departLane="best" from="190128487#1" to="-36748084#0" type="veh_passenger"/>
    <trip id="veh351" depart="1618.49" departLane="best" from="39894728#1" to="233006425#2" type="veh_passenger"/>
    <trip id="veh353" depart="1627.71" departLane="best" from="112465240#2" to="400077009" type="veh_passenger"/>
    <trip id="veh354" depart="1632.32" departLane="best" from="8366901#1" to="13277357#2" type="veh_passenger"/>
    <trip id="veh355" depart="1636.94" departLane="best" from="220232893#0" to="206720845#1" type="veh_passenger"/>
    <trip id="veh356" depart="1641.55" departLane="best" from="551619530#0" to="239593895#1" type="veh_passenger"/>
    <trip id="veh358" depart="1650.77" departLane="best" from="14328446#5" to="60175590#2" type="veh_passenger"/>
    <trip id="veh359" depart="1655.38" departLane="best" from="211436103#0" to="39894728#2" type="veh_passenger"/>
    <trip id="veh360" depart="1659.99" departLane="best" from="12298717" to="14326558#4" type="veh_passenger"/>
    <trip id="veh361" depart="1664.60" departLane="best" from="256249046#1" to="96151239#0" type="veh_passenger"/>
    <trip id="veh363" depart="1673.82" departLane="best" from="216972581#0" to="157156090#2" type="veh_passenger"/>
    <trip id="veh364" depart="1678.44" departLane="best" from="220232893#1" to="258853581#3" type="veh_passenger"/>
    <trip id="veh366" depart="1687.66" departLane="best" departSpeed="max" from="-39668885#2" to="34683791" type="veh_passenger"/>
    <trip id="veh367" depart="1692.27" departLane="best" from="239593895#1" to="128825638#4" type="veh_passenger"/>
    <trip id="veh368" depart="1696.88" departLane="best" from="38336628#2" to="-252518642#0" type="veh_passenger"/>
    <trip id="veh369" depart="1701.49" departLane="best" from="346992934#5" to="349620089" type="veh_passenger"/>
    <trip id="veh370" depart="1706.10" departLane="best" from="39678582#5" to="206720845#4" type="veh_passenger"/>
    <trip id="veh371" depart="1710.71" departLane="best" from="262616020#0" to="39894728#2" type="veh_passenger"/>
    <trip id="veh372" depart="1715.32" departLane="best" from="8367054" to="229816562" type="veh_passenger"/>
    <trip id="veh373" depart="1719.93" departLane="best" departSpeed="max" from="-207634492" to="233007929" type="veh_passenger"/>
    <trip id="veh374" depart="1724.55" departLane="best" from="256249048#1" to="448850570#7" type="veh_passenger"/>
    <trip id="veh375" depart="1729.16" departLane="best" from="448850568#0" to="212706766#0" type="veh_passenger"/>
    <trip id="veh376" depart="1733.77" departLane="best" from="332479850#1" to="207724055" type="veh_passenger"/>
    <trip id="veh377" depart="1738.38" departLane="best" from="262474849#5" to="-434878401#0" type="veh_passenger"/>
    <trip id="veh378" depart="1742.99" departLane="best" from="197434949#1" to="8366889#1" type="veh_passenger"/>
    <trip id="veh379" depart="1747.60" departLane="best" from="13848688#1" to="34683151#0" type="veh_passenger"/>
    <trip id="veh380" depart="1752.21" departLane="best" from="262474849#1" to="434878401#3" type="veh_passenger"/>
    <trip id="veh381" depart="1756.82" departLane="best" from="434872534#2" to="434879926#2" type="veh_passenger"/>
    <trip id="veh383" depart="1766.05" departLane="best" from="332479850#0" to="39668434#2" type="veh_passenger"/>
    <trip id="veh384" depart="1770.66" departLane="best" from="-226624856" to="287648900" type="veh_passenger"/>
    <trip id="veh385" depart="1775.27" departLane="best" departSpeed="max" from="548373860" to="96151239#0" type="veh_passenger"/>
    <trip id="veh387" depart="1784.49" departLane="best" from="-26119992#2" to="287648900" type="veh_passenger"/>
    <trip id="veh388" depart="1789.10" departLane="best" from="434879926#2" to="215194131#1" type="veh_passenger"/>
    <trip id="veh389" depart="1793.71" departLane="best" departSpeed="max" from="-207724055" to="39862487#0" type="veh_passenger"/>
    <trip id="veh390" depart="1798.32" departLane="best" departSpeed="max" from="128363655#0" to="190128490" type="veh_passenger"/>
    <trip id="veh392" depart="1807.55" departLane="best" from="233006425#3" to="39690472" type="veh_passenger"/>
    <trip id="veh393" depart="1812.16" departLane="best" departSpeed="max" from="-386286205" to="-26119992#8" type="veh_passenger"/>
    <trip id="veh394" depart="1816.77" departLane="best" departSpeed="max" from="-287648900" to="216891254#0" type="veh_passenger"/>
    <trip id="veh395" depart="1821.38" departLane="best" departSpeed="max" from="-548373865" to="13800986#0" type="veh_passenger"/>
    <trip id="veh396" depart="1825.99" departLane="best" departSpeed="max" from="-128363658#1" to="39888045#1" type="veh_passenger"/>
    <trip id="veh397" depart="1830.60" departLane="best" from="482276568" to="332479850#0" type="veh_passenger"/>
    <trip id="veh398" depart="1835.21" departLane="best" from="-349620089" to="212706766#0" type="veh_passenger"/>
    <trip id="veh400" depart="1844.43" departLane="best" from="26119992#8" to="210339821#1" type="veh_passenger"/>
    <trip id="veh402" depart="1853.66" departLane="best" departSpeed="max" from="-39690472" to="206720845#2" type="veh_passenger"/>
    <trip id="veh404" depart="1862.88" departLane="best" from="239593897" to="26119992#7" type="veh_passenger"/>
    <trip id="veh405" depart="1867.49" departLane="best" from="8367104#3" to="14326558#2" type="veh_passenger"/>
    <trip id="veh406" depart="1872.10" departLane="best" from="8366893#1" to="307804461#2" type="veh_passenger"/>
    <trip id="veh407" depart="1876.71" departLane="best" from="112465240#3" to="26119992#11" type="veh_passenger"/>
    <trip id="veh408" depart="1881.32" departLane="best" from="290230304" to="386286206#1" type="veh_passenger"/>
    <trip id="veh409" depart="1885.93" departLane="best" departSpeed="max" from="-207724055" to="262616020#1" type="veh_passenger"/>
    <trip id="veh410" depart="1890.55" departLane="best" from="210365858#2" to="484592256#2" type="veh_passenger"/>
    <trip id="veh412" depart="1899.77" departLane="best" from="258853581#4" to="167487357#0" type="veh_passenger"/>
    <trip id="veh413" depart="1904.38" departLane="best" from="26119992#6" to="280786930#1" type="veh_passenger"/>
    <trip id="veh414" depart="1908.99" departLane="best" departSpeed="max" from="280786930#0" to="38336628#0" type="veh_passenger"/>
    <trip id="veh415" depart="1913.60" departLane="best" from="262474849#8" to="434872534#2" type="veh_passenger"/>
    <trip id="veh416" depart="1918.21" departLane="best" from="26119992#11" to="484592256#1" type="veh_passenger"/>
    <trip id="veh418" depart="1927.43" departLane="best" from="167487357#0" to="26207695#0" type="veh_passenger"/>
    <trip id="veh419" depart="1932.04" departLane="best" from="34607518#2" to="-262474849#5" type="veh_passenger"/>
    <trip id="veh420" depart="1936.66" departLane="best" departSpeed="max" from="128363655#0" to="386286210" type="veh_passenger"/>
    <trip id="veh421" depart="1941.27" departLane="best" departSpeed="max" from="-386286206#1" to="-39669380" type="veh_passenger"/>
    <trip id="veh422" depart="1945.88" departLane="best" from="39894728#0" to="13801868#0" type="veh_passenger"/>
    <trip id="veh423" depart="1950.49" departLane="best" from="39888372#0" to="217628815" type="veh_passenger"/>
    <trip id="veh424" depart="1955.10" departLane="best" from="39670508#1" to="386286206#1" type="veh_passenger"/>
    <trip id="veh425" depart="1959.71" departLane="best" from="13848688#1" to="-349620091" type="veh_passenger"/>
    <trip id="veh426" depart="1964.32" departLane="best" from="608420971#1" to="-39888367#2" type="veh_passenger"/>
    <trip id="veh427" depart="1968.93" departLane="best" from="608420973" to="434879926#2" type="veh_passenger"/>
    <trip id="veh428" depart="1973.54" departLane="best" from="332479850#3" to="8367089#1" type="veh_passenger"/>
    <trip id="veh429" depart="1978.16" departLane="best" from="608421700#0" to="39888045#1" type="veh_passenger"/>
    <trip id="veh430" depart="1982.77" departLane="best" from="167487526" to="332053082#2" type="veh_passenger"/>
    <trip id="veh432" depart="1991.99" departLane="best" from="39888368#3" to="60175941#2" type="veh_passenger"/>
    <trip id="veh433" depart="1996.60" departLane="best" from="-26119992#8" to="128825638#4" type="veh_passenger"/>
    <trip id="veh434" depart="2001.21" departLane="best" from="-14333888#3" to="482261339#0" type="veh_passenger"/>
    <trip id="veh435" depart="2005.82" departLane="best" from="229802211" to="551619530#1" type="veh_passenger"/>
    <trip id="veh437" depart="2015.04" departLane="best" from="39888370" to="548373865" type="veh_passenger"/>
    <trip id="veh438" depart="2019.66" departLane="best" from="128823187#2" to="207724055" type="veh_passenger"/>
    <trip id="veh439" depart="2024.27" departLane="best" from="-28193999#2" to="60175941#7" type="veh_passenger"/>
    <trip id="veh440" depart="2028.88" departLane="best" from="128823189#0" to="227982906#4" type="veh_passenger"/>
    <trip id="veh441" depart="2033.49" departLane="best" from="-26119992#11" to="482264026#1" type="veh_passenger"/>
    <trip id="veh442" depart="2038.10" departLane="best" departSpeed="max" from="-278570718#3" to="215301977#0" type="veh_passenger"/>
    <trip id="veh443" depart="2042.71" departLane="best" from="262945890#4" to="386286205" type="veh_passenger"/>
    <trip id="veh444" depart="2047.32" departLane="best" from="60175941#0" to="210328137" type="veh_passenger"/>
    <trip id="veh445" depart="2051.93" departLane="best" from="346992934#2" to="-434878401#0" type="veh_passenger"/>
    <trip id="veh446" depart="2056.54" departLane="best" from="14328446#5" to="-280786930#0" type="veh_passenger"/>
    <trip id="veh447" depart="2061.16" departLane="best" from="60175941#3" to="-210365858#3" type="veh_passenger"/>
    <trip id="veh448" depart="2065.77" departLane="best" from="60175941#3" to="434879921#2" type="veh_passenger"/>
    <trip id="veh450" depart="2074.99" departLane="best" from="216972801#0" to="8367070#3" type="veh_passenger"/>
    <trip id="veh451" depart="2079.60" departLane="best" from="14326464#7" to="207634492" type="veh_passenger"/>
    <trip id="veh452" depart="2084.21" departLane="best" departSpeed="max" from="-39668885#2" to="-386286210" type="veh_passenger"/>
    <trip id="veh454" depart="2093.43" departLane="best" from="262579556#2" to="30405557#0" type="veh_passenger"/>
    <trip id="veh455" depart="2098.04" departLane="best" departSpeed="max" from="256431162#0" to="-156211618#0" type="veh_passenger"/>
    <trip id="veh456" depart="2102.66" departLane="best" from="394998026#1" to="13277357#2" type="veh_passenger"/>
    <trip id="veh457" depart="2107.27" departLane="best" from="-262474849#4" to="26119992#10" type="veh_passenger"/>
    <trip id="veh458" depart="2111.88" departLane="best" from="-226624856" to="39669069#0" type="veh_passenger"/>
    <trip id="veh459" depart="2116.49" departLane="best" departSpeed="max" from="-39865747" to="128363658#1" type="veh_passenger"/>
    <trip id="veh460" depart="2121.10" departLane="best" from="434879926#0" to="14333500#1" type="veh_passenger"/>
    <trip id="veh461" depart="2125.71" departLane="best" departSpeed="max" from="-287648900" to="482296563#0" type="veh_passenger"/>
    <trip id="veh462" depart="2130.32" departLane="best" from="-128362570#1" to="434879926#1" type="veh_passenger"/>
    <trip id="veh463" depart="2134.93" departLane="best" departSpeed="max" from="-287648900" to="-39668885#1" type="veh_passenger"/>
    <trip id="veh464" depart="2139.54" departLane="best" departSpeed="max" from="-548373865" to="-8367070#0" type="veh_passenger"/>
    <trip id="veh465" depart="2144.15" departLane="best" from="262474849#9" to="-207634523#0" type="veh_passenger"/>
    <trip id="veh467" depart="2153.38" departLane="best" from="-434879926#1" to="14333321#2" type="veh_passenger"/>
    <trip id="veh468" depart="2157.99" departLane="best" departSpeed="max" from="-386286206#1" to="-255778743#0" type="veh_passenger"/>
    <trip id="veh469" depart="2162.60" departLane="best" from="346992934#7" to="216972801#0" type="veh_passenger"/>
    <trip id="veh470" depart="2167.21" departLane="best" from="38336628#4" to="252518642#1" type="veh_passenger"/>
    <trip id="veh471" depart="2171.82" departLane="best" from="-26119992#8" to="233055818" type="veh_passenger"/>
    <trip id="veh472" depart="2176.43" departLane="best" from="60175941#0" to="-239593895#1" type="veh_passenger"/>
    <trip id="veh473" depart="2181.04" departLane="best" from="38336628#5" to="448850570#3" type="veh_passenger"/>
    <trip id="veh474" depart="2185.65" departLane="best" from="215210562#0" to="216159806#0" type="veh_passenger"/>
    <trip id="veh476" depart="2194.88" departLane="best" from="206720845#6" to="207634505#0" type="veh_passenger"/>
    <trip id="veh477" depart="2199.49" departLane="best" from="290230304" to="227888631#1" type="veh_passenger"/>
    <trip id="veh478" depart="2204.10" departLane="best" from="482296563#0" to="-26119992#5" type="veh_passenger"/>
    <trip id="veh479" depart="2208.71" departLane="best" from="-252518644#1" to="262623003#1" type="veh_passenger"/>
    <trip id="veh480" depart="2213.32" departLane="best" departSpeed="max" from="-216891254#1" to="14326464#4" type="veh_passenger"/>
    <trip id="veh481" depart="2217.93" departLane="best" from="26119992#4" to="26119844#0" type="veh_passenger"/>
    <trip id="veh482" depart="2222.54" departLane="best" from="216159806#1" to="215301977#0" type="veh_passenger"/>
    <trip id="veh483" depart="2227.15" departLane="best" from="258853581#3" to="-280786930#0" type="veh_passenger"/>
    <trip id="veh484" depart="2231.77" departLane="best" from="307804461#0" to="434878401#3" type="veh_passenger"/>
    <trip id="veh485" depart="2236.38" departLane="best" from="262474849#1" to="39669380" type="veh_passenger"/>
    <trip id="veh486" depart="2240.99" departLane="best" from="332479850#0" to="128363658#0" type="veh_passenger"/>
    <trip id="veh487" depart="2245.60" departLane="best" from="13848688#1" to="215301977#0" type="veh_passenger"/>
    <trip id="veh489" depart="2254.82" departLane="best" from="14326558#1" to="-434860177#1" type="veh_passenger"/>
    <trip id="veh490" depart="2259.43" departLane="best" from="578561126" to="-26119992#11" type="veh_passenger"/>
    <trip id="veh491" depart="2264.04" departLane="best" from="-26119992#10" to="385795770#0" type="veh_passenger"/>
    <trip id="veh492" depart="2268.65" departLane="best" from="39678582#7" to="26119880-AddedOffRampEdge" type="veh_passenger"/>
    <trip id="veh493" depart="2273.27" departLane="best" from="256165014" to="26119900#1" type="veh_passenger"/>
    <trip id="veh494" depart="2277.88" departLane="best" from="13836129#2" to="-386286210" type="veh_passenger"/>
    <trip id="veh496" depart="2287.10" departLane="best" departSpeed="max" from="349620090#0" to="448850570#6" type="veh_passenger"/>
    <trip id="veh497" depart="2291.71" departLane="best" from="332479850#1" to="8366889#1" type="veh_passenger"/>
    <trip id="veh499" depart="2300.93" departLane="best" from="252518836#0" to="128363657" type="veh_passenger"/>
    <trip id="veh500" depart="2305.54" departLane="best" from="262474849#6" to="128363659#1" type="veh_passenger"/>
    <trip id="veh502" depart="2314.76" departLane="best" from="14326493#4" to="39668885#2" type="veh_passenger"/>
    <trip id="veh503" depart="2319.38" departLane="best" from="252518642#1" to="39888367#2" type="veh_passenger"/>
    <trip id="veh504" depart="2323.99" departLane="best" departSpeed="max" from="39896043" to="8367058#1" type="veh_passenger"/>
    <trip id="veh505" depart="2328.60" departLane="best" from="39888045#1" to="27149319#0" type="veh_passenger"/>
    <trip id="veh506" depart="2333.21" departLane="best" from="26207695#1" to="-207634523#0" type="veh_passenger"/>
    <trip id="veh507" depart="2337.82" departLane="best" from="59525257#0" to="39895304#1" type="veh_passenger"/>
    <trip id="veh508" depart="2342.43" departLane="best" departSpeed="max" from="-96151239#3" to="112465240#1" type="veh_passenger"/>
    <trip id="veh510" depart="2351.65" departLane="best" from="13848688#1" to="-128825640#0" type="veh_passenger"/>
    <trip id="veh511" depart="2356.26" departLane="best" from="434879926#0" to="26119992#11" type="veh_passenger"/>
    <trip id="veh512" depart="2360.88" departLane="best" departSpeed="max" from="14327868#0" to="-39888368#3" type="veh_passenger"/>
    <trip id="veh513" depart="2365.49" departLane="best" from="26119992#4" to="-210365858#0" type="veh_passenger"/>
    <trip id="veh514" depart="2370.10" departLane="best" from="346992934#7" to="128363658#0" type="veh_passenger"/>
    <trip id="veh515" depart="2374.71" departLane="best" from="14333321#2" to="156211619" type="veh_passenger"/>
    <trip id="veh516" depart="2379.32" departLane="best" from="14326558#0" to="38336628#0" type="veh_passenger"/>
    <trip id="veh517" depart="2383.93" departLane="best" from="38336628#4" to="26119992#2" type="veh_passenger"/>
    <trip id="veh520" depart="2397.76" departLane="best" from="262579556#1" to="220232893#1" type="veh_passenger"/>
    <trip id="veh521" depart="2402.38" departLane="best" from="167487357#0" to="14326464#3" type="veh_passenger"/>
    <trip id="veh522" depart="2406.99" departLane="best" from="36748084#0" to="-349620091" type="veh_passenger"/>
    <trip id="veh523" depart="2411.60" departLane="best" from="14333888#1" to="14326493#2" type="veh_passenger"/>
    <trip id="veh524" depart="2416.21" departLane="best" departSpeed="max" from="280786930#0" to="220232893#2" type="veh_passenger"/>
    <trip id="veh525" depart="2420.82" departLane="best" from="262623003#1" to="-252518642#1" type="veh_passenger"/>
    <trip id="veh526" depart="2425.43" departLane="best" departSpeed="max" from="14327351#0" to="262474849#7" type="veh_passenger"/>
    <trip id="veh527" depart="2430.04" departLane="best" departSpeed="max" from="-128363658#1" to="14326572#0" type="veh_passenger"/>
    <trip id="veh528" depart="2434.65" departLane="best" departSpeed="max" from="-551619530#1" to="14333500#0" type="veh_passenger"/>
    <trip id="veh529" depart="2439.26" departLane="best" departSpeed="max" from="-128363658#1" to="386286206#1" type="veh_passenger"/>
    <trip id="veh530" depart="2443.88" departLane="best" departSpeed="max" from="-386286206#1" to="197464424#2" type="veh_passenger"/>
    <trip id="veh531" depart="2448.49" departLane="best" from="307804461#1" to="233007929" type="veh_passenger"/>
    <trip id="veh532" depart="2453.10" departLane="best" from="-227982906#4" to="448850568#0" type="veh_passenger"/>
    <trip id="veh533" depart="2457.71" departLane="best" departSpeed="max" from="-207634492" to="-146190183#0" type="veh_passenger"/>
    <trip id="veh534" depart="2462.32" departLane="best" departSpeed="max" from="548373860" to="448850568#0" type="veh_passenger"/>
    <trip id="veh535" depart="2466.93" departLane="best" from="252518644#2" to="26119992#6" type="veh_passenger"/>
    <trip id="veh536" depart="2471.54" departLane="best" from="31060242#0" to="210328137" type="veh_passenger"/>
    <trip id="veh538" depart="2480.76" departLane="best" from="13801868#1" to="39888043#1" type="veh_passenger"/>
    <trip id="veh539" depart="2485.38" departLane="best" from="26119880-AddedOffRampEdge" to="39896053" type="veh_passenger"/>
    <trip id="veh540" depart="2489.99" departLane="best" departSpeed="max" from="548373860" to="-262474849#4" type="veh_passenger"/>
    <trip id="veh541" depart="2494.60" departLane="best" departSpeed="max" from="39896043" to="13277357#1" type="veh_passenger"/>
    <trip id="veh542" depart="2499.21" departLane="best" from="13848688#1" to="14333733#1" type="veh_passenger"/>
    <trip id="veh545" depart="2513.04" departLane="best" from="482296561" to="167057944#0" type="veh_passenger"/>
    <trip id="veh546" depart="2517.65" departLane="best" departSpeed="max" from="34607518#0" to="39894728#1" type="veh_passenger"/>
    <trip id="veh547" depart="2522.26" departLane="best" from="39862511" to="128825641#0" type="veh_passenger"/>
    <trip id="veh548" depart="2526.87" departLane="best" departSpeed="max" from="-287648900" to="124539825" type="veh_passenger"/>
    <trip id="veh549" depart="2531.49" departLane="best" from="258853579#0" to="39668885#1" type="veh_passenger"/>
    <trip id="veh550" depart="2536.10" departLane="best" from="262474849#5" to="-8367073" type="veh_passenger"/>
    <trip id="veh551" depart="2540.71" departLane="best" from="38336628#2" to="229802211" type="veh_passenger"/>
    <trip id="veh552" depart="2545.32" departLane="best" from="36740122" to="39668885#1" type="veh_passenger"/>
    <trip id="veh553" depart="2549.93" departLane="best" from="167487363#1" to="59525257#0" type="veh_passenger"/>
    <trip id="veh554" depart="2554.54" departLane="best" from="233006425#1" to="287648900" type="veh_passenger"/>
    <trip id="veh555" depart="2559.15" departLane="best" from="26119992#10" to="-434860177#0" type="veh_passenger"/>
    <trip id="veh556" depart="2563.76" departLane="best" from="-220232893#2" to="212706766#0" type="veh_passenger"/>
    <trip id="veh557" depart="2568.37" departLane="best" from="128823187#2" to="14326464#4" type="veh_passenger"/>
    <trip id="veh558" depart="2572.99" departLane="best" from="-210365858#4" to="239593895#1" type="veh_passenger"/>
    <trip id="veh559" depart="2577.60" departLane="best" from="128825641#0" to="215301975" type="veh_passenger"/>
    <trip id="veh560" depart="2582.21" departLane="best" from="-212706762#1" to="39896053" type="veh_passenger"/>
    <trip id="veh561" depart="2586.82" departLane="best" from="-239593895#0" to="448850570#1" type="veh_passenger"/>
    <trip id="veh562" depart="2591.43" departLane="best" from="434872534#4" to="27149319#1" type="veh_passenger"/>
    <trip id="veh563" depart="2596.04" departLane="best" from="220232893#2" to="39690472" type="veh_passenger"/>
    <trip id="veh565" depart="2605.26" departLane="best" from="39671211" to="304688480#0" type="veh_passenger"/>
    <trip id="veh566" depart="2609.87" departLane="best" from="133211822#2" to="216972581#3" type="veh_passenger"/>
    <trip id="veh568" depart="2619.10" departLane="best" from="-26119992#5" to="482296562" type="veh_passenger"/>
    <trip id="veh569" depart="2623.71" departLane="best" departSpeed="max" from="13849088#0" to="36748084#0" type="veh_passenger"/>
    <trip id="veh570" depart="2628.32" departLane="best" departSpeed="max" from="211314340#0" to="-551619530#0" type="veh_passenger"/>
    <trip id="veh571" depart="2632.93" departLane="best" from="-482296560#1" to="211436103#0" type="veh_passenger"/>
    <trip id="veh572" depart="2637.54" departLane="best" from="156211620" to="256165014" type="veh_passenger"/>
    <trip id="veh573" depart="2642.15" departLane="best" from="124539825" to="207724055" type="veh_passenger"/>
    <trip id="veh574" depart="2646.76" departLane="best" from="13848688#1" to="262474849#6" type="veh_passenger"/>
    <trip id="veh575" depart="2651.37" departLane="best" departSpeed="max" from="39658536#0" to="304684297#0" type="veh_passenger"/>
    <trip id="veh576" depart="2655.99" departLane="best" departSpeed="max" from="-216891254#1" to="-262474849#8" type="veh_passenger"/>
    <trip id="veh577" depart="2660.60" departLane="best" departSpeed="max" from="280786930#0" to="14326493#3" type="veh_passenger"/>
    <trip id="veh578" depart="2665.21" departLane="best" from="332479850#2" to="307804461#1" type="veh_passenger"/>
    <trip id="veh579" depart="2669.82" departLane="best" from="482296561" to="448850570#9" type="veh_passenger"/>
    <trip id="veh581" depart="2679.04" departLane="best" departSpeed="max" from="-287648900" to="167057944#0" type="veh_passenger"/>
    <trip id="veh582" depart="2683.65" departLane="best" from="608421700#0" to="346992934#0" type="veh_passenger"/>
    <trip id="veh583" depart="2688.26" departLane="best" departSpeed="max" from="14327351#0" to="262474849#4" type="veh_passenger"/>
    <trip id="veh585" depart="2697.49" departLane="best" from="39679497" to="332053082#0" type="veh_passenger"/>
    <trip id="veh586" depart="2702.10" departLane="best" from="39888372#7" to="385795770#0" type="veh_passenger"/>
    <trip id="veh587" depart="2706.71" departLane="best" from="28193999#1" to="256249048#0" type="veh_passenger"/>
    <trip id="veh588" depart="2711.32" departLane="best" departSpeed="max" from="26207794#0" to="210339821#0" type="veh_passenger"/>
    <trip id="veh589" depart="2715.93" departLane="best" from="14326487#3" to="167487363#1" type="veh_passenger"/>
    <trip id="veh590" depart="2720.54" departLane="best" from="-394998026#2" to="128363658#0" type="veh_passenger"/>
    <trip id="veh591" depart="2725.15" departLane="best" from="60175941#2" to="220232893#2" type="veh_passenger"/>
    <trip id="veh592" depart="2729.76" departLane="best" departSpeed="max" from="-39896053" to="-39888043#0" type="veh_passenger"/>
    <trip id="veh593" depart="2734.37" departLane="best" from="-26119992#3" to="39670422#2" type="veh_passenger"/>
    <trip id="veh594" depart="2738.98" departLane="best" from="39894728#3" to="482261339#0" type="veh_passenger"/>
    <trip id="veh595" depart="2743.60" departLane="best" departSpeed="max" from="-207634492" to="146190183#0" type="veh_passenger"/>
    <trip id="veh596" depart="2748.21" departLane="best" from="38336627#1" to="-39669069#0" type="veh_passenger"/>
    <trip id="veh597" depart="2752.82" departLane="best" from="14326558#3" to="-482261338#1" type="veh_passenger"/>
    <trip id="veh598" depart="2757.43" departLane="best" from="39894728#0" to="39670422#2" type="veh_passenger"/>
    <trip id="veh600" depart="2766.65" departLane="best" from="156211619" to="207724055" type="veh_passenger"/>
    <trip id="veh601" depart="2771.26" departLane="best" departSpeed="max" from="280786930#0" to="128825641#1" type="veh_passenger"/>
    <trip id="veh602" depart="2775.87" departLane="best" from="167487357#1" to="14326493#3" type="veh_passenger"/>
    <trip id="veh603" depart="2780.48" departLane="best" departSpeed="max" from="349620090#0" to="215200352#1" type="veh_passenger"/>
    <trip id="veh606" depart="2794.32" departLane="best" from="39894728#3" to="174689857" type="veh_passenger"/>
    <trip id="veh607" depart="2798.93" departLane="best" from="190128487#1" to="14326493#0" type="veh_passenger"/>
    <trip id="veh608" depart="2803.54" departLane="best" from="14326572#0" to="256277806#0" type="veh_passenger"/>
    <trip id="veh609" depart="2808.15" departLane="best" from="608420973" to="39894728#0" type="veh_passenger"/>
    <trip id="veh610" depart="2812.76" departLane="best" from="39669178#2" to="-39888045#1" type="veh_passenger"/>
    <trip id="veh611" depart="2817.37" departLane="best" from="-51230332#0" to="292119381" type="veh_passenger"/>
    <trip id="veh612" depart="2821.98" departLane="best" from="448850568#0" to="26119880-AddedOffRampEdge" type="veh_passenger"/>
    <trip id="veh614" depart="2831.21" departLane="best" from="434860177#1" to="14326493#3" type="veh_passenger"/>
    <trip id="veh615" depart="2835.82" departLane="best" departSpeed="max" from="38336627#0" to="14326464#3" type="veh_passenger"/>
    <trip id="veh616" depart="2840.43" departLane="best" from="482276569#1" to="-39888372#4" type="veh_passenger"/>
    <trip id="veh617" depart="2845.04" departLane="best" from="156211619" to="60175941#7" type="veh_passenger"/>
    <trip id="veh618" depart="2849.65" departLane="best" from="-39888372#3" to="215210562#2" type="veh_passenger"/>
    <trip id="veh620" depart="2858.87" departLane="best" departSpeed="max" from="59525260#0" to="434872534#2" type="veh_passenger"/>
    <trip id="veh622" depart="2868.10" departLane="best" from="-28193999#0" to="14326493#4" type="veh_passenger"/>
    <trip id="veh623" depart="2872.71" departLane="best" from="39888372#8" to="34683791" type="veh_passenger"/>
    <trip id="veh624" depart="2877.32" departLane="best" from="-28193999#0" to="349620090#3" type="veh_passenger"/>
    <trip id="veh625" depart="2881.93" departLane="best" from="167487363#0" to="-128363658#0" type="veh_passenger"/>
    <trip id="veh626" depart="2886.54" departLane="best" from="-252518642#1" to="13800986#0" type="veh_passenger"/>
    <trip id="veh627" depart="2891.15" departLane="best" from="39894728#3" to="26119844#0" type="veh_passenger"/>
    <trip id="veh628" depart="2895.76" departLane="best" departSpeed="max" from="34607518#0" to="256277806#0" type="veh_passenger"/>
    <trip id="veh630" depart="2904.98" departLane="best" from="128823187#0" to="-252518644#1" type="veh_passenger"/>
    <trip id="veh631" depart="2909.59" departLane="best" from="14333321#2" to="39690472" type="veh_passenger"/>
    <trip id="veh632" depart="2914.21" departLane="best" departSpeed="max" from="174689856" to="-349620090#2" type="veh_passenger"/>
    <trip id="veh633" depart="2918.82" departLane="best" from="482276569#1" to="262474849#5" type="veh_passenger"/>
    <trip id="veh634" depart="2923.43" departLane="best" from="-13277357#1" to="252518644#0" type="veh_passenger"/>
    <trip id="veh635" depart="2928.04" departLane="best" departSpeed="max" from="-481849358" to="-39888370" type="veh_passenger"/>
    <trip id="veh637" depart="2937.26" departLane="best" from="-452076637#3" to="210328137" type="veh_passenger"/>
    <trip id="veh638" depart="2941.87" departLane="best" from="262616020#1" to="-262474849#2" type="veh_passenger"/>
    <trip id="veh639" depart="2946.48" departLane="best" from="8366889#0" to="-26119992#11" type="veh_passenger"/>
    <trip id="veh640" depart="2951.09" departLane="best" from="215301977#1" to="239593895#1" type="veh_passenger"/>
    <trip id="veh641" depart="2955.71" departLane="best" departSpeed="max" from="14327351#0" to="216972581#0" type="veh_passenger"/>
    <trip id="veh643" depart="2964.93" departLane="best" departSpeed="max" from="-548373865" to="-14333888#1" type="veh_passenger"/>
    <trip id="veh644" depart="2969.54" departLane="best" from="394998026#3" to="157156090#2" type="veh_passenger"/>
    <trip id="veh645" depart="2974.15" departLane="best" from="34607518#3" to="287648900" type="veh_passenger"/>
    <trip id="veh646" depart="2978.76" departLane="best" departSpeed="max" from="13848688#0" to="-252518642#0" type="veh_passenger"/>
    <trip id="veh647" depart="2983.37" departLane="best" from="216972801#1" to="39888372#4" type="veh_passenger"/>
    <trip id="veh648" depart="2987.98" departLane="best" departSpeed="max" from="-386286206#1" to="39670518#1" type="veh_passenger"/>
    <trip id="veh649" depart="2992.59" departLane="best" from="190128487#4" to="34683151#0" type="veh_passenger"/>
    <trip id="veh650" depart="2997.21" departLane="best" from="26119992#3" to="39888372#1" type="veh_passenger"/>
    <trip id="veh651" depart="3001.82" departLane="best" departSpeed="max" from="-216891254#1" to="39670508#0-AddedOnRampEdge" type="veh_passenger"/>
    <trip id="veh652" depart="3006.43" departLane="best" departSpeed="max" from="174689856" to="14326558#2" type="veh_passenger"/>
    <trip id="veh653" depart="3011.04" departLane="best" departSpeed="max" from="-207634492" to="124539828#1" type="veh_passenger"/>
    <trip id="veh654" depart="3015.65" departLane="best" departSpeed="max" from="-207634492" to="60175590#2" type="veh_passenger"/>
    <trip id="veh655" depart="3020.26" departLane="best" from="215194131#1" to="8367114#2" type="veh_passenger"/>
    <trip id="veh656" depart="3024.87" departLane="best" from="216972581#3" to="13800986#0" type="veh_passenger"/>
    <trip id="veh657" depart="3029.48" departLane="best" from="35203817#1" to="112631504#1" type="veh_passenger"/>
    <trip id="veh658" depart="3034.09" departLane="best" from="14326464#6" to="39670518#3" type="veh_passenger"/>
    <trip id="veh659" depart="3038.71" departLane="best" from="434878401#3" to="14333500#5" type="veh_passenger"/>
    <trip id="veh660" depart="3043.32" departLane="best" from="-262474849#2" to="174689857" type="veh_passenger"/>
    <trip id="veh661" depart="3047.93" departLane="best" from="448860910#1" to="386286205" type="veh_passenger"/>
    <trip id="veh662" depart="3052.54" departLane="best" from="482240915#1" to="206720845#4" type="veh_passenger"/>
    <trip id="veh663" depart="3057.15" departLane="best" from="210365858#3" to="59525257#0" type="veh_passenger"/>
    <trip id="veh664" depart="3061.76" departLane="best" from="215200349#1" to="39888043#1" type="veh_passenger"/>
    <trip id="veh665" depart="3066.37" departLane="best" from="332479850#4" to="-26119992#8" type="veh_passenger"/>
    <trip id="veh666" depart="3070.98" departLane="best" from="258853579#0" to="39894728#3" type="veh_passenger"/>
    <trip id="veh668" depart="3080.21" departLane="best" from="-252518642#1" to="307804461#3" type="veh_passenger"/>
    <trip id="veh669" depart="3084.82" departLane="best" from="128825638#1" to="262474849#9" type="veh_passenger"/>
    <trip id="veh670" depart="3089.43" departLane="best" from="434879926#0" to="167487357#0" type="veh_passenger"/>
    <trip id="veh672" depart="3098.65" departLane="best" from="8366901#1" to="608420970#0" type="veh_passenger"/>
    <trip id="veh673" depart="3103.26" departLane="best" departSpeed="max" from="-233007929" to="287648900" type="veh_passenger"/>
    <trip id="veh674" depart="3107.87" departLane="best" from="14326493#0" to="39888043#1" type="veh_passenger"/>
    <trip id="veh675" depart="3112.48" departLane="best" from="280786930#1" to="608420970#2" type="veh_passenger"/>
    <trip id="veh676" depart="3117.09" departLane="best" departSpeed="max" from="-287648900" to="262616020#4" type="veh_passenger"/>
    <trip id="veh677" depart="3121.70" departLane="best" from="38336628#5" to="-212706762#1" type="veh_passenger"/>
    <trip id="veh678" depart="3126.32" departLane="best" from="-220232893#1" to="39670518#1" type="veh_passenger"/>
    <trip id="veh679" depart="3130.93" departLane="best" from="14326493#3" to="206720845#1" type="veh_passenger"/>
    <trip id="veh680" depart="3135.54" departLane="best" from="233055818" to="262616020#0" type="veh_passenger"/>
    <trip id="veh681" depart="3140.15" departLane="best" from="280786930#1" to="608420970#0" type="veh_passenger"/>
    <trip id="veh682" depart="3144.76" departLane="best" from="252518642#1" to="256277806#2" type="veh_passenger"/>
    <trip id="veh683" depart="3149.37" departLane="best" from="14327351#2" to="304684297#1" type="veh_passenger"/>
    <trip id="veh684" depart="3153.98" departLane="best" from="34607518#6" to="233006425#3" type="veh_passenger"/>
    <trip id="veh685" depart="3158.59" departLane="best" from="14326572#3" to="26119900#1" type="veh_passenger"/>
    <trip id="veh686" depart="3163.20" departLane="best" from="-8367070#2" to="13802005" type="veh_passenger"/>
    <trip id="veh687" depart="3167.82" departLane="best" from="167487357#1" to="96151239#0" type="veh_passenger"/>
    <trip id="veh688" depart="3172.43" departLane="best" from="124539828#1" to="551619530#1" type="veh_passenger"/>
    <trip id="veh690" depart="3181.65" departLane="best" from="434872534#2" to="215301975" type="veh_passenger"/>
    <trip id="veh691" depart="3186.26" departLane="best" from="482264025#1" to="215200349#0" type="veh_passenger"/>
    <trip id="veh693" depart="3195.48" departLane="best" departSpeed="max" from="142214759#0" to="-26119992#0" type="veh_passenger"/>
    <trip id="veh695" depart="3204.70" departLane="best" from="434860177#1" to="36748083#3" type="veh_passenger"/>
    <trip id="veh696" depart="3209.32" departLane="best" from="595164143#3" to="287648900" type="veh_passenger"/>
    <trip id="veh697" depart="3213.93" departLane="best" from="-262474849#1" to="128362570#1" type="veh_passenger"/>
    <trip id="veh699" depart="3223.15" departLane="best" from="-146190183#0" to="26119880" type="veh_passenger"/>
    <trip id="veh700" depart="3227.76" departLane="best" from="14326493#4" to="39888043#1" type="veh_passenger"/>
    <trip id="veh701" depart="3232.37" departLane="best" from="220232893#0" to="262945890#3" type="veh_passenger"/>
    <trip id="veh703" depart="3241.59" departLane="best" from="95841157" to="374346170" type="veh_passenger"/>
    <trip id="veh704" depart="3246.20" departLane="best" from="39888370" to="-26119992#5" type="veh_passenger"/>
    <trip id="veh705" depart="3250.82" departLane="best" from="608421700#3" to="30405557#0" type="veh_passenger"/>
    <trip id="veh706" depart="3255.43" departLane="best" from="167487363#1" to="332479850#1" type="veh_passenger"/>
    <trip id="veh707" depart="3260.04" departLane="best" departSpeed="max" from="142214759#0" to="452076637#0" type="veh_passenger"/>
    <trip id="veh708" depart="3264.65" departLane="best" from="-39658536#1" to="643548708" type="veh_passenger"/>
    <trip id="veh709" depart="3269.26" departLane="best" from="14333888#6" to="548373865" type="veh_passenger"/>
    <trip id="veh710" depart="3273.87" departLane="best" from="-307804461#3" to="-482296560#1" type="veh_passenger"/>
    <trip id="veh711" depart="3278.48" departLane="best" from="133211822#3" to="36748083#3" type="veh_passenger"/>
    <trip id="veh712" depart="3283.09" departLane="best" departSpeed="max" from="142214759#0" to="60175941#3" type="veh_passenger"/>
    <trip id="veh714" depart="3292.32" departLane="best" departSpeed="max" from="-548373865" to="287648900" type="veh_passenger"/>
    <trip id="veh716" depart="3301.54" departLane="best" from="210851328#5" to="-548373860" type="veh_passenger"/>
    <trip id="veh718" depart="3310.76" departLane="best" from="258853581#3" to="434872534#4" type="veh_passenger"/>
    <trip id="veh719" depart="3315.37" departLane="best" from="233006425#0" to="39895285#2" type="veh_passenger"/>
    <trip id="veh720" depart="3319.98" departLane="best" from="262474849#2" to="39669178#1" type="veh_passenger"/>
    <trip id="veh721" depart="3324.59" departLane="best" from="14328446#6" to="287648900" type="veh_passenger"/>
    <trip id="veh722" depart="3329.20" departLane="best" from="210365858#3" to="28193999#1" type="veh_passenger"/>
    <trip id="veh725" depart="3343.04" departLane="best" from="28193999#1" to="14326558#3" type="veh_passenger"/>
    <trip id="veh727" depart="3352.26" departLane="best" from="156211620" to="220232893#0" type="veh_passenger"/>
    <trip id="veh728" depart="3356.87" departLane="best" from="13277357#1" to="374346169" type="veh_passenger"/>
    <trip id="veh729" depart="3361.48" departLane="best" from="34607518#4" to="434879926#2" type="veh_passenger"/>
    <trip id="veh730" depart="3366.09" departLane="best" from="8366889#0" to="-39669069#0" type="veh_passenger"/>
    <trip id="veh731" depart="3370.70" departLane="best" from="13277357#5" to="216969809#3" type="veh_passenger"/>
    <trip id="veh732" depart="3375.31" departLane="best" departSpeed="max" from="-96151239#3" to="13277357#4" type="veh_passenger"/>
    <trip id="veh733" depart="3379.93" departLane="best" from="-26119992#10" to="14326558#0" type="veh_passenger"/>
    <trip id="veh734" depart="3384.54" departLane="best" from="14326572#1" to="275860210" type="veh_passenger"/>
    <trip id="veh735" depart="3389.15" departLane="best" from="-482296560#1" to="448850570#2" type="veh_passenger"/>
    <trip id="veh737" depart="3398.37" departLane="best" departSpeed="max" from="38336627#0" to="233006425#2" type="veh_passenger"/>
    <trip id="veh738" depart="3402.98" departLane="best" from="215194131#0" to="233006425#3" type="veh_passenger"/>
    <trip id="veh739" depart="3407.59" departLane="best" from="128825640#0" to="-197434949#1" type="veh_passenger"/>
    <trip id="veh740" depart="3412.20" departLane="best" from="60175941#0" to="239593895#0" type="veh_passenger"/>
    <trip id="veh741" depart="3416.81" departLane="best" from="608420973" to="128363658#0" type="veh_passenger"/>
    <trip id="veh742" depart="3421.43" departLane="best" from="14326464#2" to="-255778743#0" type="veh_passenger"/>
    <trip id="veh744" depart="3430.65" departLane="best" from="262474849#5" to="216972581#0" type="veh_passenger"/>
    <trip id="veh745" depart="3435.26" departLane="best" from="216972581#0" to="434878401#0" type="veh_passenger"/>
    <trip id="veh747" depart="3444.48" departLane="best" departSpeed="max" from="34607518#0" to="39668885#2" type="veh_passenger"/>
    <trip id="veh748" depart="3449.09" departLane="best" from="14326493#3" to="207634492" type="veh_passenger"/>
    <trip id="veh749" depart="3453.70" departLane="best" from="239593895#0" to="112635323#2" type="veh_passenger"/>
    <trip id="veh750" depart="3458.31" departLane="best" from="220232893#1" to="-26119992#5" type="veh_passenger"/>
    <trip id="veh751" depart="3462.93" departLane="best" from="112635323#0" to="8367114#1" type="veh_passenger"/>
    <trip id="veh752" depart="3467.54" departLane="best" from="28193881" to="-36748084#0" type="veh_passenger"/>
    <trip id="veh753" depart="3472.15" departLane="best" from="8366889#0" to="207634492" type="veh_passenger"/>
    <trip id="veh754" depart="3476.76" departLane="best" from="39668434#0" to="156211618#0" type="veh_passenger"/>
    <trip id="veh755" depart="3481.37" departLane="best" from="60175590#0" to="39658536#2" type="veh_passenger"/>
    <trip id="veh757" depart="3490.59" departLane="best" from="210851328#1" to="-252518642#1" type="veh_passenger"/>
    <trip id="veh758" depart="3495.20" departLane="best" from="-280786930#1" to="14333733#1" type="veh_passenger"/>
    <trip id="veh759" depart="3499.81" departLane="best" from="206720845#0" to="215331280#1" type="veh_passenger"/>
    <trip id="veh760" depart="3504.43" departLane="best" from="13836129#0" to="262945890#5" type="veh_passenger"/>
    <trip id="veh761" depart="3509.04" departLane="best" departSpeed="max" from="-36748083#3" to="8367114#3" type="veh_passenger"/>
    <trip id="veh762" depart="3513.65" departLane="best" from="34683791" to="14326558#4" type="veh_passenger"/>
    <trip id="veh763" depart="3518.26" departLane="best" departSpeed="max" from="13848688#0" to="39895304#0" type="veh_passenger"/>
    <trip id="veh764" depart="3522.87" departLane="best" from="216159806#3" to="36740122" type="veh_passenger"/>
    <trip id="veh765" depart="3527.48" departLane="best" from="128363661" to="39888372#8" type="veh_passenger"/>
    <trip id="veh766" depart="3532.09" departLane="best" from="14326493#4" to="332053082#2" type="veh_passenger"/>
    <trip id="veh768" depart="3541.31" departLane="best" from="39668434#2" to="38336628#1" type="veh_passenger"/>
    <trip id="veh769" depart="3545.92" departLane="best" departSpeed="max" from="30405423" to="-210339821#0" type="veh_passenger"/>
    <trip id="veh770" depart="3550.54" departLane="best" from="206720845#1" to="8366889#0" type="veh_passenger"/>
    <trip id="veh771" depart="3555.15" departLane="best" from="38336628#5" to="39670508#0-AddedOnRampEdge" type="veh_passenger"/>
    <trip id="veh772" depart="3559.76" departLane="best" from="252518836#0" to="38336628#0" type="veh_passenger"/>
    <trip id="veh773" depart="3564.37" departLane="best" from="255778743#3" to="-548373860" type="veh_passenger"/>
    <trip id="veh775" depart="3573.59" departLane="best" from="39895290#1" to="-39888372#6" type="veh_passenger"/>
    <trip id="veh776" depart="3578.20" departLane="best" from="28193881" to="-210365858#1" type="veh_passenger"/>
    <trip id="veh777" depart="3582.81" departLane="best" from="60175941#2" to="-349620089" type="veh_passenger"/>
    <trip id="veh779" depart="3592.04" departLane="best" departSpeed="max" from="14328446#0" to="39670508#0" type="veh_passenger"/>
    <trip id="veh780" depart="3596.65" departLane="best" departSpeed="max" from="548373860" to="448850570#9" type="veh_passenger"/>
</routes>
